localalias/__init__.py
localalias/__main__.py
localalias/app.py
localalias/commands.py
localalias/errors.py
localalias/utils/__init__.py
localalias/utils/core.py
localalias/utils/log.py
localalias/utils/xdg.py
localalias-2.0.0.dist-info/METADATA
localalias-2.0.0.dist-info/RECORD
localalias-2.0.0.dist-info/WHEEL
localalias-2.0.0.dist-info/entry_points.txt
localalias-2.0.0.dist-info/top_level.txt
