Metadata-Version: 2.1
Name: localalias
Version: 2.0.0
Summary: A light-weight shell wrapper that allows you to create per-directoy command aliases.
Home-page: https://github.com/bbugyi200/localalias
Author: Bryan M Bugyi
Author-email: bryanbugyi34@gmail.com
License: MIT license
Keywords: localalias
Platform: UNKNOWN
Classifier: Development Status :: 2 - Pre-Alpha
Classifier: Intended Audience :: Developers
Classifier: License :: OSI Approved :: MIT License
Classifier: Natural Language :: English
Classifier: Programming Language :: Python :: 3
Classifier: Programming Language :: Python :: 3.4
Classifier: Programming Language :: Python :: 3.5
Classifier: Programming Language :: Python :: 3.6
Requires-Dist: pygments
